[1,["57L9isgtVE5bxLUIvK+F/Z","2fxdFhpHZByrwv1MrFTelv@6c48a","48/oq0MfVF26f98sgfVZsK@6c48a","e78mRuNhRHlp5yKpUsKo+W@f9941","94GdAJ6yxBSas7D26luerr@f9941","f0kyCQqEdCaL/Tm+xxbgE1@f9941","50g/P+2a5I2qm4OMUM6bpe@f9941","2fxdFhpHZByrwv1MrFTelv@f9941","9elTjSgW9AvLG5rgdFeTCK@f9941","ee2Vy45m9Lr7tEM693sZ9F@f9941","90nUHsOvJDta5ySxkzvE8q@f9941","e7qCnfw0FB3Io5MpWaPSpg@f9941","cfDcfn34xLHaVTEP/yAohH@f9941","4eZdp/Yj1DrZ9pZXFJcC3Q@f9941","c7XHZ0RmJIQbPgfWwaYKCY@f9941","24K/A73jFNcLmGwaMmzYiJ@f9941","506DPX5yRBpZZ9OW40hYz6@f9941","7eV+bb4b9Js4inpK0ct8wm@f9941","48/oq0MfVF26f98sgfVZsK@f9941","dakJH0foFIBbJmhon/qoSS@f9941","94GdAJ6yxBSas7D26luerr@6c48a","e78mRuNhRHlp5yKpUsKo+W@6c48a","f0kyCQqEdCaL/Tm+xxbgE1@6c48a"],["node","_spriteFrame","_textureSource","_font","root","txtHave","txtPrice","txtBuy","nameBooster","icon","_target","data"],["cc.SpriteFrame",["cc.Node",["_name","_layer","_components","_prefab","_lpos","_parent","_children","_lscale"],1,9,4,5,1,2,5],["cc.Label",["_string","_actualFontSize","_fontSize","_lineHeight","_isSystemFontUsed","_overflow","_enableWrapText","_enableOutline","node","__prefab","_color","_shadowOffset","_outlineColor"],-5,1,4,5,5,5],["cc.Node",["_name","_layer","_parent","_components","_prefab","_lpos","_lscale"],1,1,12,4,5,5],["cc.Sprite",["_sizeMode","_isTrimmedMode","node","__prefab","_spriteFrame"],1,1,4,6],["b749f2CzvhLCpYzucd6p2lM",["key","node","__prefab"],2,1,4],["cc.Prefab",["_name"],2],["cc.UITransform",["node","__prefab","_contentSize"],3,1,4,5],["cc.CompPrefabInfo",["fileId"],2],["3567fm6txhIkLfBVYm3tFje",["node","__prefab","icon","nameBooster","txtBuy","txtPrice","txtHave","iconBoosters"],3,1,4,1,1,1,1,1,12],["cc.PrefabInfo",["fileId","instance","targetOverrides","nestedPrefabInstanceRoots","root","asset"],-1,1,1],["cc.Button",["_transition","node","__prefab","clickEvents","_target"],2,1,4,9,1],["cc.ClickEvent",["_componentId","handler","target"],1,1]],[[8,0,2],[7,0,1,2,1],[10,0,1,2,3,4,5,5],[3,0,1,2,3,4,5,3],[4,2,3,4,1],[1,0,1,5,6,2,3,4,3],[1,0,1,5,2,3,4,7,3],[4,0,2,3,4,2],[5,0,1,2,2],[6,0,2],[1,0,1,6,2,3,4,3],[1,0,1,5,2,3,3],[3,0,1,2,3,4,3],[3,0,1,2,3,4,5,6,3],[9,0,1,2,3,4,5,6,7,1],[4,0,1,2,3,3],[11,0,1,2,3,4,2],[12,0,1,2,3],[5,1,2,1],[2,0,1,2,3,5,6,4,8,9,10,8],[2,0,1,2,3,5,4,8,9,11,7],[2,0,1,2,3,5,4,8,9,10,7],[2,0,1,2,3,4,7,8,9,12,7]],[[[{"name":"frame 02","rect":{"x":0,"y":0,"width":195,"height":195},"offset":{"x":0,"y":0},"originalSize":{"width":195,"height":195},"rotated":false,"capInsets":[0,0,0,0],"vertices":{"rawPosition":[-97.5,-97.5,0,97.5,-97.5,0,-97.5,97.5,0,97.5,97.5,0],"indexes":[0,1,2,2,1,3],"uv":[0,195,195,195,0,0,195,0],"nuv":[0,0,1,0,0,1,1,1],"minPos":{"x":-97.5,"y":-97.5,"z":0},"maxPos":{"x":97.5,"y":97.5,"z":0}},"packable":true,"pixelsToUnit":100,"pivot":{"x":0.5,"y":0.5},"meshType":0}],[0],0,[0],[2],[1]],[[{"name":"Second_Chance","rect":{"x":0,"y":0,"width":168,"height":161},"offset":{"x":0,"y":0},"originalSize":{"width":168,"height":161},"rotated":false,"capInsets":[0,0,0,0],"vertices":{"rawPosition":[-84,-80.5,0,84,-80.5,0,-84,80.5,0,84,80.5,0],"indexes":[0,1,2,2,1,3],"uv":[0,161,168,161,0,0,168,0],"nuv":[0,0,1,0,0,1,1,1],"minPos":{"x":-84,"y":-80.5,"z":0},"maxPos":{"x":84,"y":80.5,"z":0}},"packable":true,"pixelsToUnit":100,"pivot":{"x":0.5,"y":0.5},"meshType":0}],[0],0,[0],[2],[2]],[[[9,"ItemBooster"],[10,"ItemBooster",33554432,[-9,-10,-11,-12,-13,-14],[[1,-2,[0,"5e/9yE6NBMRbpyFBL/La9n"],[5,487,261]],[14,-8,[0,"77mR34CoxAU46qdWjh3bcu"],-7,-6,-5,-4,-3,[[5,6,7,8,9,10,11,12,13,14,null,15],6,6,6,6,6,6,6,6,6,6,0,6]]],[2,"63xxSYUhZAPofByrpFQ4D0",null,null,null,-1,0],[1,-342.817,-205.5,0]],[5,"btnBuy",33554432,1,[-19,-20,-21],[[1,-15,[0,"e6DEIU88ZB+KBGXatLNad2"],[5,195,195]],[4,-16,[0,"32XcTN9mFLzYC5ex3weT9T"],4],[16,1,-18,[0,"f6f3MjItdBGpD9SajCCch+"],[[17,"3567fm6txhIkLfBVYm3tFje","BtnBuy",1]],-17]],[2,"e8eY6pxHNDSL2OxeE9PfZb",null,null,null,1,0],[1,211.633,-16.219,0]],[5,"frame",33554432,1,[-24],[[1,-22,[0,"354kreVh5GE7cwWXIlBW+t"],[5,246,68]],[7,2,-23,[0,"07iOH60n5HTYJFvAUbkTCQ"],1]],[2,"9aUEmysodMpYEe0HLNbx85",null,null,null,1,0],[1,-11.249,-61.792,0]],[12,"txtHave",33554432,3,[[[1,-25,[0,"1dIFNcetFKoJTPzU3KuDd3"],[5,187.4049530029297,52.61]],-26,[8,"YouHave",-27,[0,"87Kx8WZBVDCYo8UdQWMMGX"]]],4,1,4],[2,"7a2hyiaydGCLrfmVU8lq4V",null,null,null,1,0]],[3,"nameBooster",33554432,1,[[[1,-28,[0,"00iNltSKFB2KEuUfPObWLW"],[5,254.386546875,44.736]],-29,[18,-30,[0,"12fWvznchJaoDT1e927gf4"]]],4,1,4],[2,"2fspnjbNRAMY+m2Xe2l1Fu",null,null,null,1,0],[1,-2.055,105.931,0]],[3,"txtBuy",33554432,1,[[[1,-31,[0,"781frwUJxEXIqnsDVXYgd9"],[5,179.09114843749995,65.239]],-32,[8,"buy",-33,[0,"79U/2FIcJJtKZvsDqGM5mP"]]],4,1,4],[2,"05g2hbtIJFmquZqeS7i4OA",null,null,null,1,0],[1,-2.055,30.828,0]],[6,"button 08",33554432,2,[[1,-34,[0,"c6sGIDfbxIhYDT5ZU41dCP"],[5,229,229]],[4,-35,[0,"a81dvAs71K3bxDXkaTcKD5"],2]],[2,"7a0A7+yENIELXZP/86lY7J",null,null,null,1,0],[1,2.296,-1.048,0],[1,0.7,0.7,1]],[11,"bg",33554432,1,[[1,-36,[0,"4bnsgkChpJFYgfYawx2tmN"],[5,487,261]],[7,2,-37,[0,"0aCNdVqopKX79bPsKPodeY"],0]],[2,"74g8I9UFNDnL075ft+KRSp",null,null,null,1,0]],[6,"Icon_dimond",33554432,2,[[1,-38,[0,"28NZf6cG5LY4ZDPouT49Id"],[5,249,217]],[4,-39,[0,"42xgQu2P1NPbtx6loBNxO0"],3]],[2,"ac/EZ7ifpB96G06wkAjgib",null,null,null,1,0],[1,44.101,-68.294,0],[1,0.38,0.38,1]],[3,"txtPrice",33554432,2,[[[1,-40,[0,"27QBxaN4BDMI+pwLH9V+UN"],[5,110.34397888183594,83.38]],-41],4,1],[2,"01/D5j53hAnJxUXOTfn/Ow",null,null,null,1,0],[1,0.041,6.612,0]],[13,"icon",33554432,1,[[[1,-42,[0,"e2hnI0jy5IMqbFK4u6C5jK"],[5,256,256]],-43],4,1],[2,"73DX6XuShC2oEGIyfD498+",null,null,null,1,0],[1,-205.296,-18.837,0],[1,0.8,0.8,1]],[19,"You have 0",37,37,37,2,false,false,4,[0,"b1aho+igZM/4Iqv+dl3BD8"],[4,4278609112]],[20,"Double profit",38,37,37,2,false,5,[0,"5eiFTiNLtNaarD77zIjDDe"],[0,0,-4]],[21,"Buy 3",56,55,55,2,false,6,[0,"5drfwgLIZORrvgejDmmykg"],[4,4278609112]],[22,"100",63,63,63,false,true,10,[0,"fc2Gf8YoVJfbsLNJd82o7z"],[4,4279716888]],[15,2,false,11,[0,"be4ibfqPpNk55b3CcxPdQV"]]],0,[0,4,1,0,0,1,0,5,12,0,6,15,0,7,14,0,8,13,0,9,16,0,0,1,0,-1,8,0,-2,3,0,-3,5,0,-4,6,0,-5,2,0,-6,11,0,0,2,0,0,2,0,10,7,0,0,2,0,-1,7,0,-2,9,0,-3,10,0,0,3,0,0,3,0,-1,4,0,0,4,0,-2,12,0,0,4,0,0,5,0,-2,13,0,0,5,0,0,6,0,-2,14,0,0,6,0,0,7,0,0,7,0,0,8,0,0,8,0,0,9,0,0,9,0,0,10,0,-2,15,0,0,11,0,-2,16,0,11,1,43],[0,0,0,0,0,0,0,0,0,0,0,0,0,0,0,0,12,13,14,15,16],[1,1,1,1,1,-1,-2,-3,-4,-5,-6,-7,-8,-9,-10,-12,3,3,3,3,1],[3,4,5,6,7,8,9,10,11,12,13,14,15,16,17,18,0,0,0,0,19]],[[{"name":"frame 03","rect":{"x":0,"y":0,"width":246,"height":68},"offset":{"x":0,"y":0},"originalSize":{"width":246,"height":68},"rotated":false,"capInsets":[36,34,36,34],"vertices":{"rawPosition":[-123,-34,0,123,-34,0,-123,34,0,123,34,0],"indexes":[0,1,2,2,1,3],"uv":[0,68,246,68,0,0,246,0],"nuv":[0,0,1,0,0,1,1,1],"minPos":{"x":-123,"y":-34,"z":0},"maxPos":{"x":123,"y":34,"z":0}},"packable":true,"pixelsToUnit":100,"pivot":{"x":0.5,"y":0.5},"meshType":0}],[0],0,[0],[2],[20]],[[{"name":"frame 01","rect":{"x":0,"y":0,"width":487,"height":261},"offset":{"x":0,"y":0},"originalSize":{"width":487,"height":261},"rotated":false,"capInsets":[0,0,0,0],"vertices":{"rawPosition":[-243.5,-130.5,0,243.5,-130.5,0,-243.5,130.5,0,243.5,130.5,0],"indexes":[0,1,2,2,1,3],"uv":[0,261,487,261,0,0,487,0],"nuv":[0,0,1,0,0,1,1,1],"minPos":{"x":-243.5,"y":-130.5,"z":0},"maxPos":{"x":243.5,"y":130.5,"z":0}},"packable":true,"pixelsToUnit":100,"pivot":{"x":0.5,"y":0.5},"meshType":0}],[0],0,[0],[2],[21]],[[{"name":"button 08","rect":{"x":0,"y":0,"width":229,"height":229},"offset":{"x":0,"y":0},"originalSize":{"width":229,"height":229},"rotated":false,"capInsets":[0,0,0,0],"vertices":{"rawPosition":[-114.5,-114.5,0,114.5,-114.5,0,-114.5,114.5,0,114.5,114.5,0],"indexes":[0,1,2,2,1,3],"uv":[0,229,229,229,0,0,229,0],"nuv":[0,0,1,0,0,1,1,1],"minPos":{"x":-114.5,"y":-114.5,"z":0},"maxPos":{"x":114.5,"y":114.5,"z":0}},"packable":true,"pixelsToUnit":100,"pivot":{"x":0.5,"y":0.5},"meshType":0}],[0],0,[0],[2],[22]]]]
