[1,["ab/edsdWxCTZc8iOsPjFYW","7dj5uJT9FMn6OrOOx83tfK@f9941","88AXWgXw9N569GxZAxrkKk@f9941","abkDY2fRJHRJdOwkQucB+X@f9941","88AXWgXw9N569GxZAxrkKk@6c48a","abkDY2fRJHRJdOwkQucB+X@6c48a"],["node","_spriteFrame","_textureSource","root","data","_defaultClip"],[["cc.Node",["_name","_layer","_components","_prefab","_parent","_children","_lpos"],1,9,4,1,2,5],"cc.SpriteFrame",["cc.Sprite",["_sizeMode","node","__prefab","_spriteFrame","_color"],2,1,4,6,5],["cc.Prefab",["_name"],2],["cc.UITransform",["node","__prefab","_contentSize"],3,1,4,5],["cc.CompPrefabInfo",["fileId"],2],["cc.Widget",["_enabled","_alignFlags","_originalWidth","_originalHeight","_alignMode","node","__prefab"],-2,1,4],["cc.PrefabInfo",["fileId","instance","targetOverrides","nestedPrefabInstanceRoots","root","asset"],-1,1,1],["cc.Mask",["_type","_inverted","node","__prefab"],1,1,4],["cc.Graphics",["node","__prefab","_fillColor"],3,1,4,5],["cc.BlockInputEvents",["node","__prefab"],3,1,4],["cc.Animation",["playOnLoad","node","__prefab","_clips","_defaultClip"],2,1,4,3,6]],[[5,0,2],[4,0,1,2,1],[7,0,1,2,3,4,5,5],[0,0,1,4,2,3,3],[6,0,1,2,3,4,5,6,6],[2,1,2,3,1],[3,0,2],[0,0,1,5,2,3,3],[0,0,1,4,5,2,3,3],[0,0,1,4,2,3,6,3],[8,0,1,2,3,3],[9,0,1,2,1],[2,0,1,2,4,3,2],[10,0,1,1],[11,0,1,2,3,4,2]],[[[[6,"tutorialUI"],[7,"tutorialUI",33554432,[-4,-5,-6],[[1,-2,[0,"4ajf+0SflJL5HchHQIqxgO"],[5,1920,1080]],[4,false,45,100,100,1,-3,[0,"abGT0QrUNNPJz2DId+tGKT"]]],[2,"a2s6MnYY1AY7Qh6pMVnjZ9",null,null,null,-1,0]],[8,"mask",33554432,1,[-10],[[1,-7,[0,"940uLSOtNPnZmfwDp7XXOV"],[5,339,339]],[10,1,true,-8,[0,"0aRuyK2apJirNaTSi4K0tT"]],[11,-9,[0,"84qL/9EURKaZe/jNzu7ds1"],[4,16777215]]],[2,"16w3yFnSVIDrKYQ6e7efdy",null,null,null,1,0]],[3,"bg",33554432,2,[[1,-11,[0,"cfRYd4KOJOuaCqwCzA4Oto"],[5,5000,3500]],[4,false,45,100,100,1,-12,[0,"5c4dop7ztNKqbPnOMkqKSl"]],[12,0,-13,[0,"4b3BwIWEtP77oulzZzt4Pe"],[4,2516582400],0],[13,-14,[0,"45wsDZm3RKXqXvYdlY2Fhd"]]],[2,"0bWKhZJUJL/Iz54h0t9icX",null,null,null,1,0]],[9,"HandPoint",33554432,1,[[1,-15,[0,"6ahsWnDRtDFZ3/u5t+3rGr"],[5,164,172]],[5,-16,[0,"911Logo+BELrIHcPoCUwaS"],2],[14,true,-17,[0,"66Bb0bDyRCObYhRNBzqa4O"],[3],4]],[2,"ceK+Vuj2xDuJnH4W+Cdjbo",null,null,null,1,0],[1,112.07400000000007,-119.803,0]],[3,"Shape",33554432,1,[[1,-18,[0,"e8nCRwt4JEupkOO0k++Gwf"],[5,339,360]],[5,-19,[0,"d66luCSeRNg6eNfiYHDJQh"],1]],[2,"8cNDpsIClJZJlk0lwu8AQ0",null,null,null,1,0]]],0,[0,3,1,0,0,1,0,0,1,0,-1,2,0,-2,5,0,-3,4,0,0,2,0,0,2,0,0,2,0,-1,3,0,0,3,0,0,3,0,0,3,0,0,3,0,0,4,0,0,4,0,0,4,0,0,5,0,0,5,0,4,1,19],[0,0,0,0,0],[1,1,1,-1,5],[1,2,3,0,0]],[[{"name":"Shape","rect":{"x":63,"y":46,"width":339,"height":360},"offset":{"x":0,"y":-8.5},"originalSize":{"width":465,"height":435},"rotated":false,"capInsets":[0,0,0,0],"vertices":{"rawPosition":[-169.5,-180,0,169.5,-180,0,-169.5,180,0,169.5,180,0],"indexes":[0,1,2,2,1,3],"uv":[63,389,402,389,63,29,402,29],"nuv":[0.13548387096774195,0.06666666666666667,0.864516129032258,0.06666666666666667,0.13548387096774195,0.8942528735632184,0.864516129032258,0.8942528735632184],"minPos":{"x":-169.5,"y":-180,"z":0},"maxPos":{"x":169.5,"y":180,"z":0}},"packable":true,"pixelsToUnit":100,"pivot":{"x":0.5,"y":0.5},"meshType":0}],[1],0,[0],[2],[4]],[[{"name":"HandPoint","rect":{"x":0,"y":0,"width":164,"height":172},"offset":{"x":0,"y":0},"originalSize":{"width":164,"height":172},"rotated":false,"capInsets":[0,0,0,0],"vertices":{"rawPosition":[-82,-86,0,82,-86,0,-82,86,0,82,86,0],"indexes":[0,1,2,2,1,3],"uv":[0,172,164,172,0,0,164,0],"nuv":[0,0,1,0,0,1,1,1],"minPos":{"x":-82,"y":-86,"z":0},"maxPos":{"x":82,"y":86,"z":0}},"packable":true,"pixelsToUnit":100,"pivot":{"x":0.5,"y":0.5},"meshType":0}],[1],0,[0],[2],[5]]]]
